{
    "_checkpoint": {
        "global_record": {
            "index": -1,
            "infractions": {
                "collisions_layout": 0.0,
                "collisions_pedestrian": 0.011595142752177878,
                "collisions_vehicle": 0.009821689108545134,
                "outside_route_lanes": 0.0,
                "red_light": 0.00786220408216051,
                "route_dev": 0.0,
                "route_timeout": 0.0,
                "stop_infraction": 0.0,
                "vehicle_blocked": 0.0
            },
            "meta": {},
            "route_id": -1,
            "scores": {
                "score_composed": 88.0,
                "score_penalty": 0.8800000000000001,
                "score_route": 100.0
            },
            "status": "Completed"
        },
        "progress": [
            10,
            10
        ],
        "records": [
            {
                "index": 0,
                "infractions": {
                    "collisions_layout": [],
                    "collisions_pedestrian": [],
                    "collisions_vehicle": [],
                    "outside_route_lanes": [],
                    "red_light": [],
                    "route_dev": [],
                    "route_timeout": [],
                    "stop_infraction": [],
                    "vehicle_blocked": []
                },
                "meta": {
                    "duration_game": 411.7500061355531,
                    "duration_system": 3627.6636674404144,
                    "route_length": 1071.0281341479306
                },
                "route_id": "RouteScenario_16",
                "scores": {
                    "score_composed": 100.0,
                    "score_penalty": 1.0,
                    "score_route": 100.0
                },
                "status": "Completed"
            },
            {
                "index": 1,
                "infractions": {
                    "collisions_layout": [],
                    "collisions_pedestrian": [
                        "Agent collided against object with type=walker.pedestrian.0019 and id=545 at (x=193.938, y=118.928, z=0.034), at time=194.65000290051103"
                    ],
                    "collisions_vehicle": [],
                    "outside_route_lanes": [],
                    "red_light": [],
                    "route_dev": [],
                    "route_timeout": [],
                    "stop_infraction": [],
                    "vehicle_blocked": []
                },
                "meta": {
                    "duration_game": 249.0500037111342,
                    "duration_system": 2062.900108575821,
                    "route_length": 862.4300893683893
                },
                "route_id": "RouteScenario_17",
                "scores": {
                    "score_composed": 50.0,
                    "score_penalty": 0.5,
                    "score_route": 100.0
                },
                "status": "Completed"
            },
            {
                "index": 2,
                "infractions": {
                    "collisions_layout": [],
                    "collisions_pedestrian": [],
                    "collisions_vehicle": [
                        "Agent collided against object with type=vehicle.mustang.mustang and id=966 at (x=-125.706, y=9.086, z=0.033), at time=433.1000064536929"
                    ],
                    "outside_route_lanes": [],
                    "red_light": [],
                    "route_dev": [],
                    "route_timeout": [],
                    "stop_infraction": [],
                    "vehicle_blocked": []
                },
                "meta": {
                    "duration_game": 532.4000079333782,
                    "duration_system": 4564.548468828201,
                    "route_length": 1018.1548091661475
                },
                "route_id": "RouteScenario_18",
                "scores": {
                    "score_composed": 60.0,
                    "score_penalty": 0.6,
                    "score_route": 100.0
                },
                "status": "Completed"
            },
            {
                "index": 3,
                "infractions": {
                    "collisions_layout": [],
                    "collisions_pedestrian": [],
                    "collisions_vehicle": [],
                    "outside_route_lanes": [],
                    "red_light": [],
                    "route_dev": [],
                    "route_timeout": [],
                    "stop_infraction": [],
                    "vehicle_blocked": []
                },
                "meta": {
                    "duration_game": 362.85000540688634,
                    "duration_system": 2980.2167825698853,
                    "route_length": 1651.1240425772803
                },
                "route_id": "RouteScenario_19",
                "scores": {
                    "score_composed": 100.0,
                    "score_penalty": 1.0,
                    "score_route": 100.0
                },
                "status": "Completed"
            },
            {
                "index": 4,
                "infractions": {
                    "collisions_layout": [],
                    "collisions_pedestrian": [],
                    "collisions_vehicle": [],
                    "outside_route_lanes": [],
                    "red_light": [],
                    "route_dev": [],
                    "route_timeout": [],
                    "stop_infraction": [],
                    "vehicle_blocked": []
                },
                "meta": {
                    "duration_game": 330.9500049315393,
                    "duration_system": 3210.779462814331,
                    "route_length": 1247.5247794196757
                },
                "route_id": "RouteScenario_20",
                "scores": {
                    "score_composed": 100.0,
                    "score_penalty": 1.0,
                    "score_route": 100.0
                },
                "status": "Completed"
            },
            {
                "index": 5,
                "infractions": {
                    "collisions_layout": [],
                    "collisions_pedestrian": [],
                    "collisions_vehicle": [],
                    "outside_route_lanes": [],
                    "red_light": [],
                    "route_dev": [],
                    "route_timeout": [],
                    "stop_infraction": [],
                    "vehicle_blocked": []
                },
                "meta": {
                    "duration_game": 163.30000243335962,
                    "duration_system": 1644.249267578125,
                    "route_length": 531.0775144021973
                },
                "route_id": "RouteScenario_21",
                "scores": {
                    "score_composed": 100.0,
                    "score_penalty": 1.0,
                    "score_route": 100.0
                },
                "status": "Completed"
            },
            {
                "index": 6,
                "infractions": {
                    "collisions_layout": [],
                    "collisions_pedestrian": [],
                    "collisions_vehicle": [],
                    "outside_route_lanes": [],
                    "red_light": [],
                    "route_dev": [],
                    "route_timeout": [],
                    "stop_infraction": [],
                    "vehicle_blocked": []
                },
                "meta": {
                    "duration_game": 324.0000048279762,
                    "duration_system": 3241.819741010666,
                    "route_length": 991.7588080369975
                },
                "route_id": "RouteScenario_22",
                "scores": {
                    "score_composed": 100.0,
                    "score_penalty": 1.0,
                    "score_route": 100.0
                },
                "status": "Completed"
            },
            {
                "index": 7,
                "infractions": {
                    "collisions_layout": [],
                    "collisions_pedestrian": [],
                    "collisions_vehicle": [],
                    "outside_route_lanes": [],
                    "red_light": [
                        "Agent ran a red light 2312 at (x=21.25, y=-78.85, z=0.0) at time=13.750000204890966"
                    ],
                    "route_dev": [],
                    "route_timeout": [],
                    "stop_infraction": [],
                    "vehicle_blocked": []
                },
                "meta": {
                    "duration_game": 385.50000574439764,
                    "duration_system": 4053.312931060791,
                    "route_length": 1271.9079656924944
                },
                "route_id": "RouteScenario_23",
                "scores": {
                    "score_composed": 70.0,
                    "score_penalty": 0.7,
                    "score_route": 100.0
                },
                "status": "Completed"
            },
            {
                "index": 8,
                "infractions": {
                    "collisions_layout": [],
                    "collisions_pedestrian": [],
                    "collisions_vehicle": [],
                    "outside_route_lanes": [],
                    "red_light": [],
                    "route_dev": [],
                    "route_timeout": [],
                    "stop_infraction": [],
                    "vehicle_blocked": []
                },
                "meta": {
                    "duration_game": 779.1000116094947,
                    "duration_system": 7204.319099187851,
                    "route_length": 2101.2027349873474
                },
                "route_id": "RouteScenario_24",
                "scores": {
                    "score_composed": 100.0,
                    "score_penalty": 1.0,
                    "score_route": 100.0
                },
                "status": "Completed"
            },
            {
                "index": 9,
                "infractions": {
                    "collisions_layout": [],
                    "collisions_pedestrian": [],
                    "collisions_vehicle": [],
                    "outside_route_lanes": [],
                    "red_light": [],
                    "route_dev": [],
                    "route_timeout": [],
                    "stop_infraction": [],
                    "vehicle_blocked": []
                },
                "meta": {
                    "duration_game": 484.55000722035766,
                    "duration_system": 3799.6192333698273,
                    "route_length": 1554.57833961516
                },
                "route_id": "RouteScenario_25",
                "scores": {
                    "score_composed": 100.0,
                    "score_penalty": 1.0,
                    "score_route": 100.0
                },
                "status": "Completed"
            }
        ]
    },
    "eligible": true,
    "entry_status": "Finished",
    "labels": [
        "Avg. driving score",
        "Avg. route completion",
        "Avg. infraction penalty",
        "Collisions with pedestrians",
        "Collisions with vehicles",
        "Collisions with layout",
        "Red lights infractions",
        "Stop sign infractions",
        "Off-road infractions",
        "Route deviations",
        "Route timeouts",
        "Agent blocked"
    ],
    "sensors": [
        "carla_camera",
        "carla_camera",
        "carla_camera",
        "carla_camera",
        "carla_imu",
        "carla_gnss",
        "carla_speedometer",
        "carla_camera"
    ],
    "values": [
        "88.000",
        "100.000",
        "0.880",
        "0.012",
        "0.010",
        "0.000",
        "0.008",
        "0.000",
        "0.000",
        "0.000",
        "0.000",
        "0.000"
    ]
}