{
    "_checkpoint": {
        "global_record": {
            "index": -1,
            "infractions": {
                "collisions_layout": 0.0,
                "collisions_pedestrian": 0.0,
                "collisions_vehicle": 0.010815659189421007,
                "outside_route_lanes": 0.0,
                "red_light": 0.026337398305963593,
                "route_dev": 0.0,
                "route_timeout": 0.0,
                "stop_infraction": 0.1810869344546192,
                "vehicle_blocked": 0.0
            },
            "meta": {},
            "route_id": -1,
            "scores": {
                "score_composed": 83.0,
                "score_penalty": 0.8300000000000001,
                "score_route": 100.0
            },
            "status": "Completed"
        },
        "progress": [
            10,
            10
        ],
        "records": [
            {
                "index": 0,
                "infractions": {
                    "collisions_layout": [],
                    "collisions_pedestrian": [],
                    "collisions_vehicle": [],
                    "outside_route_lanes": [],
                    "red_light": [],
                    "route_dev": [],
                    "route_timeout": [],
                    "stop_infraction": [
                        "Agent ran a stop with id=216 at (x=-191.645, y=-105.688, z=0.055)",
                        "Agent ran a stop with id=222 at (x=-191.549, y=73.474, z=0.055)",
                        "Agent ran a stop with id=226 at (x=-268.994, y=18.56, z=0.0)",
                        "Agent ran a stop with id=210 at (x=-203.848, y=-88.267, z=0.0)"
                    ],
                    "vehicle_blocked": []
                },
                "meta": {
                    "duration_game": 502.90000749379396,
                    "duration_system": 1966.7763080596924,
                    "route_length": 1071.0281341479306
                },
                "route_id": "RouteScenario_16",
                "scores": {
                    "score_composed": 100.0,
                    "score_penalty": 1.0,
                    "score_route": 100.0
                },
                "status": "Completed"
            },
            {
                "index": 1,
                "infractions": {
                    "collisions_layout": [],
                    "collisions_pedestrian": [],
                    "collisions_vehicle": [],
                    "outside_route_lanes": [],
                    "red_light": [],
                    "route_dev": [],
                    "route_timeout": [],
                    "stop_infraction": [],
                    "vehicle_blocked": []
                },
                "meta": {
                    "duration_game": 386.10000575333834,
                    "duration_system": 1380.1675713062286,
                    "route_length": 862.4300893683893
                },
                "route_id": "RouteScenario_17",
                "scores": {
                    "score_composed": 100.0,
                    "score_penalty": 1.0,
                    "score_route": 100.0
                },
                "status": "Completed"
            },
            {
                "index": 2,
                "infractions": {
                    "collisions_layout": [],
                    "collisions_pedestrian": [],
                    "collisions_vehicle": [],
                    "outside_route_lanes": [],
                    "red_light": [
                        "Agent ran a red light 785 at (x=-112.966, y=-128.849, z=-0.0)"
                    ],
                    "route_dev": [],
                    "route_timeout": [],
                    "stop_infraction": [
                        "Agent ran a stop with id=713 at (x=106.767, y=14.1, z=0.0)",
                        "Agent ran a stop with id=701 at (x=-187.968, y=-75.541, z=0.056)"
                    ],
                    "vehicle_blocked": []
                },
                "meta": {
                    "duration_game": 672.550010021776,
                    "duration_system": 2592.5406460762024,
                    "route_length": 1018.1548091661475
                },
                "route_id": "RouteScenario_18",
                "scores": {
                    "score_composed": 70.0,
                    "score_penalty": 0.7,
                    "score_route": 100.0
                },
                "status": "Completed"
            },
            {
                "index": 3,
                "infractions": {
                    "collisions_layout": [],
                    "collisions_pedestrian": [],
                    "collisions_vehicle": [
                        "Agent collided against object with type=vehicle.audi.tt and id=1136 at (x=-131.881, y=-204.006, z=10.054)"
                    ],
                    "outside_route_lanes": [],
                    "red_light": [],
                    "route_dev": [],
                    "route_timeout": [],
                    "stop_infraction": [],
                    "vehicle_blocked": []
                },
                "meta": {
                    "duration_game": 622.8000092804432,
                    "duration_system": 2276.774916410446,
                    "route_length": 1651.1240425772803
                },
                "route_id": "RouteScenario_19",
                "scores": {
                    "score_composed": 60.0,
                    "score_penalty": 0.6,
                    "score_route": 100.0
                },
                "status": "Completed"
            },
            {
                "index": 4,
                "infractions": {
                    "collisions_layout": [],
                    "collisions_pedestrian": [],
                    "collisions_vehicle": [],
                    "outside_route_lanes": [],
                    "red_light": [],
                    "route_dev": [],
                    "route_timeout": [],
                    "stop_infraction": [
                        "Agent ran a stop with id=1199 at (x=106.767, y=14.1, z=0.0)",
                        "Agent ran a stop with id=1202 at (x=103.273, y=13.934, z=-0.0)",
                        "Agent ran a stop with id=1205 at (x=99.997, y=-14.271, z=0.0)"
                    ],
                    "vehicle_blocked": []
                },
                "meta": {
                    "duration_game": 477.65000711753964,
                    "duration_system": 1831.3560719490051,
                    "route_length": 1247.5247794196757
                },
                "route_id": "RouteScenario_20",
                "scores": {
                    "score_composed": 100.0,
                    "score_penalty": 1.0,
                    "score_route": 100.0
                },
                "status": "Completed"
            },
            {
                "index": 5,
                "infractions": {
                    "collisions_layout": [],
                    "collisions_pedestrian": [],
                    "collisions_vehicle": [],
                    "outside_route_lanes": [],
                    "red_light": [],
                    "route_dev": [],
                    "route_timeout": [],
                    "stop_infraction": [
                        "Agent ran a stop with id=1446 at (x=88.839, y=5.521, z=0.0)"
                    ],
                    "vehicle_blocked": []
                },
                "meta": {
                    "duration_game": 253.90000378340483,
                    "duration_system": 1019.5145907402039,
                    "route_length": 531.0775144021973
                },
                "route_id": "RouteScenario_21",
                "scores": {
                    "score_composed": 100.0,
                    "score_penalty": 1.0,
                    "score_route": 100.0
                },
                "status": "Completed"
            },
            {
                "index": 6,
                "infractions": {
                    "collisions_layout": [],
                    "collisions_pedestrian": [],
                    "collisions_vehicle": [],
                    "outside_route_lanes": [],
                    "red_light": [
                        "Agent ran a red light 1740 at (x=-38.65, y=100.05, z=0.0)"
                    ],
                    "route_dev": [],
                    "route_timeout": [],
                    "stop_infraction": [],
                    "vehicle_blocked": []
                },
                "meta": {
                    "duration_game": 599.350008931011,
                    "duration_system": 2400.3645617961884,
                    "route_length": 991.7588080369975
                },
                "route_id": "RouteScenario_22",
                "scores": {
                    "score_composed": 70.0,
                    "score_penalty": 0.7,
                    "score_route": 100.0
                },
                "status": "Completed"
            },
            {
                "index": 7,
                "infractions": {
                    "collisions_layout": [],
                    "collisions_pedestrian": [],
                    "collisions_vehicle": [],
                    "outside_route_lanes": [],
                    "red_light": [],
                    "route_dev": [],
                    "route_timeout": [],
                    "stop_infraction": [
                        "Agent ran a stop with id=1913 at (x=-174.338, y=-91.53, z=0.0)",
                        "Agent ran a stop with id=1929 at (x=-272.192, y=-15.06, z=0.0)",
                        "Agent ran a stop with id=1921 at (x=-205.414, y=91.087, z=0.0)"
                    ],
                    "vehicle_blocked": []
                },
                "meta": {
                    "duration_game": 802.2500119544566,
                    "duration_system": 3694.711941719055,
                    "route_length": 1271.9079656924944
                },
                "route_id": "RouteScenario_23",
                "scores": {
                    "score_composed": 100.0,
                    "score_penalty": 1.0,
                    "score_route": 100.0
                },
                "status": "Completed"
            },
            {
                "index": 8,
                "infractions": {
                    "collisions_layout": [],
                    "collisions_pedestrian": [],
                    "collisions_vehicle": [
                        "Agent collided against object with type=vehicle.mitsubishi.fusorosa and id=2300 at (x=-54.469, y=-113.137, z=0.087)"
                    ],
                    "outside_route_lanes": [],
                    "red_light": [],
                    "route_dev": [],
                    "route_timeout": [],
                    "stop_infraction": [
                        "Agent ran a stop with id=2176 at (x=88.856, y=2.008, z=0.0)",
                        "Agent ran a stop with id=2173 at (x=-256.469, y=-0.304, z=0.0)",
                        "Agent ran a stop with id=2164 at (x=-205.414, y=91.087, z=0.0)",
                        "Agent ran a stop with id=2174 at (x=103.273, y=13.934, z=-0.0)"
                    ],
                    "vehicle_blocked": []
                },
                "meta": {
                    "duration_game": 1283.950019132346,
                    "duration_system": 6496.646192073822,
                    "route_length": 2101.2027349873474
                },
                "route_id": "RouteScenario_24",
                "scores": {
                    "score_composed": 60.0,
                    "score_penalty": 0.6,
                    "score_route": 100.0
                },
                "status": "Completed"
            },
            {
                "index": 9,
                "infractions": {
                    "collisions_layout": [],
                    "collisions_pedestrian": [],
                    "collisions_vehicle": [],
                    "outside_route_lanes": [],
                    "red_light": [
                        "Agent ran a red light 2477 at (x=-179.25, y=-9.7, z=0.0)"
                    ],
                    "route_dev": [],
                    "route_timeout": [],
                    "stop_infraction": [
                        "Agent ran a stop with id=2417 at (x=88.839, y=5.521, z=0.0)",
                        "Agent ran a stop with id=2415 at (x=-256.469, y=-0.304, z=0.0)",
                        "Agent ran a stop with id=2406 at (x=-205.414, y=91.087, z=0.0)",
                        "Agent ran a stop with id=2415 at (x=-256.469, y=-0.304, z=0.0)",
                        "Agent ran a stop with id=2397 at (x=-203.918, y=-84.634, z=0.0)",
                        "Agent ran a stop with id=2408 at (x=-191.549, y=73.474, z=0.055)"
                    ],
                    "vehicle_blocked": []
                },
                "meta": {
                    "duration_game": 807.5000120326877,
                    "duration_system": 4099.920200586319,
                    "route_length": 1554.57833961516
                },
                "route_id": "RouteScenario_25",
                "scores": {
                    "score_composed": 70.0,
                    "score_penalty": 0.7,
                    "score_route": 100.0
                },
                "status": "Completed"
            }
        ]
    },
    "eligible": true,
    "entry_status": "Finished",
    "labels": [
        "Avg. driving score",
        "Avg. route completion",
        "Avg. infraction penalty",
        "Collisions with pedestrians",
        "Collisions with vehicles",
        "Collisions with layout",
        "Red lights infractions",
        "Stop sign infractions",
        "Off-road infractions",
        "Route deviations",
        "Route timeouts",
        "Agent blocked"
    ],
    "sensors": [
        "carla_camera",
        "carla_camera",
        "carla_camera",
        "carla_imu",
        "carla_gnss",
        "carla_speedometer",
        "carla_camera",
        "carla_lidar"
    ],
    "values": [
        "83.000",
        "100.000",
        "0.830",
        "0.000",
        "0.011",
        "0.000",
        "0.026",
        "0.181",
        "0.000",
        "0.000",
        "0.000",
        "0.000"
    ]
}